avocado_vt/__init__.py
avocado_vt/discovery.py
avocado_vt/loader.py
avocado_vt/options.py
avocado_vt/test.py
avocado_vt/utils.py
avocado_vt/conf.d/vt.conf
avocado_vt/conf.d/vt_joblock.conf
avocado_vt/plugins/__init__.py
avocado_vt/plugins/vt.py
avocado_vt/plugins/vt_bootstrap.py
avocado_vt/plugins/vt_init.py
avocado_vt/plugins/vt_joblock.py
avocado_vt/plugins/vt_list.py
avocado_vt/plugins/vt_list_archs.py
avocado_vt/plugins/vt_list_guests.py
avocado_vt/plugins/vt_resolver.py
avocado_vt/plugins/vt_runner.py
avocado_vt/plugins/vt_settings.py
virttest/RFBDes.py
virttest/__init__.py
virttest/_wrappers.py
virttest/arch.py
virttest/asset.py
virttest/base_installer.py
virttest/bootstrap.py
virttest/build_helper.py
virttest/cartesian_config.py
virttest/ceph.py
virttest/compat.py
virttest/cpu.py
virttest/curl.py
virttest/data_dir.py
virttest/defaults.py
virttest/env_process.py
virttest/error_context.py
virttest/error_event.py
virttest/funcatexit.py
virttest/gluster.py
virttest/graphical_console.py
virttest/guest_agent.py
virttest/http_server.py
virttest/installer.py
virttest/ip_sniffing.py
virttest/iscsi.py
virttest/kernel_interface.py
virttest/libvirt_cgroup.py
virttest/libvirt_installer.py
virttest/libvirt_remote.py
virttest/libvirt_storage.py
virttest/libvirt_version.py
virttest/libvirt_vm.py
virttest/libvirtd_decorator.py
virttest/logging_manager.py
virttest/lvm.py
virttest/lvsb.py
virttest/lvsb_base.py
virttest/lvsbs.py
virttest/migration.py
virttest/migration_template.py
virttest/nbd.py
virttest/nfs.py
virttest/nvme.py
virttest/openvswitch.py
virttest/ovirt.py
virttest/ovs_utils.py
virttest/postprocess_iozone.py
virttest/ppm_utils.py
virttest/propcan.py
virttest/qemu_capabilities.py
virttest/qemu_installer.py
virttest/qemu_io.py
virttest/qemu_migration.py
virttest/qemu_monitor.py
virttest/qemu_qtree.py
virttest/qemu_storage.py
virttest/qemu_virtio_port.py
virttest/qemu_vm.py
virttest/remote.py
virttest/remote_build.py
virttest/scan_autotest_results.py
avocado_framework_plugin_vt-109.0.dist-info/LICENSE
avocado_framework_plugin_vt-109.0.dist-info/METADATA
avocado_framework_plugin_vt-109.0.dist-info/WHEEL
avocado_framework_plugin_vt-109.0.dist-info/entry_points.txt
avocado_framework_plugin_vt-109.0.dist-info/top_level.txt
avocado_framework_plugin_vt-109.0.dist-info/RECORD
